streambotcore/__init__.py
streambotcore/bot_discord.py
streambotcore/bot_twitch.py
streambotcore/core.py
streambotcore/loader.py
streambotcore/utils.py
streambotcore-0.6.dist-info/METADATA
streambotcore-0.6.dist-info/WHEEL
streambotcore-0.6.dist-info/top_level.txt
streambotcore-0.6.dist-info/RECORD
