Metadata-Version: 2.4
Name: streambotcore
Version: 0.6
Summary: Unified modular Discord and Twitch bot framework
Author: AmongTheCouch23
Author-email: AmongTheCouch_Studios@hotmail.com
Classifier: Programming Language :: Python :: 3
Classifier: License :: OSI Approved :: MIT License
Classifier: Operating System :: OS Independent
Requires-Python: >=3.8
Requires-Dist: discord.py
Requires-Dist: twitchio
Dynamic: author
Dynamic: author-email
Dynamic: classifier
Dynamic: requires-dist
Dynamic: requires-python
Dynamic: summary
